dcdljeu/ceb.py
dcdljeu/mlpl.py
dcdljeu/tlm_dcdl.txt
dcdljeu/tlm_dcdl_sort.txt
dcdljeu-2.0.0.dist-info/METADATA
dcdljeu-2.0.0.dist-info/WHEEL
dcdljeu-2.0.0.dist-info/RECORD
