Metadata-Version: 2.1
Name: dcdljeu
Version: 2.0.0
Summary: Un solveur du jeu Compte Est Bon et Mot Le Plus Long issu de Des Chiffres et Des Lettres
License: MIT
Author: RadoTheProgrammer
Author-email: rado@arazakar.com
Requires-Python: >=3.12,<4.0
Classifier: License :: OSI Approved :: MIT License
Classifier: Programming Language :: Python :: 3
Classifier: Programming Language :: Python :: 3.12
